{"openapi":"3.0.1","info":{"title":"Booking Service APIs","description":"API documentation for booking service","version":"1.0"},"servers":[{"url":"http://localhost:8082","description":"Generated server url"}],"tags":[{"name":"Booking","description":"The Booking API"},{"name":"Booking Passenger","description":"The Booking Passenger API"},{"name":"Seat Inventory","description":"The Seat Inventory API"},{"name":"Passenger","description":"The Passenger API"}],"paths":{"/seat-inventories/{id}":{"get":{"tags":["Seat Inventory"],"summary":"Get a seat inventory by ID","description":"Returns a single seat inventory","operationId":"getSeatInventoryById","parameters":[{"name":"id","in":"path","required":true,"schema":{"type":"integer","format":"int64"}}],"responses":{"404":{"description":"Seat inventory not found","content":{"*/*":{"schema":{"$ref":"#/components/schemas/SeatInventory"}}}},"200":{"description":"Successfully retrieved seat inventory","content":{"*/*":{"schema":{"$ref":"#/components/schemas/SeatInventory"}}}}}},"put":{"tags":["Seat Inventory"],"summary":"Update an existing seat inventory","description":"Updates an existing seat inventory","operationId":"updateSeatInventory","parameters":[{"name":"id","in":"path","required":true,"schema":{"type":"integer","format":"int64"}}],"requestBody":{"content":{"application/json":{"schema":{"$ref":"#/components/schemas/SeatInventory"}}},"required":true},"responses":{"200":{"description":"OK","content":{"*/*":{"schema":{"$ref":"#/components/schemas/SeatInventory"}}}}}},"delete":{"tags":["Seat Inventory"],"summary":"Delete a seat inventory","description":"Deletes a seat inventory","operationId":"deleteSeatInventory","parameters":[{"name":"id","in":"path","required":true,"schema":{"type":"integer","format":"int64"}}],"responses":{"200":{"description":"OK"}}}},"/passengers/{id}":{"get":{"tags":["Passenger"],"summary":"Get a passenger by ID","description":"Returns a single passenger","operationId":"getPassengerById","parameters":[{"name":"id","in":"path","required":true,"schema":{"type":"integer","format":"int64"}}],"responses":{"200":{"description":"Successfully retrieved passenger","content":{"*/*":{"schema":{"$ref":"#/components/schemas/Passenger"}}}},"404":{"description":"Passenger not found","content":{"*/*":{"schema":{"$ref":"#/components/schemas/Passenger"}}}}}},"put":{"tags":["Passenger"],"summary":"Update an existing passenger","description":"Updates an existing passenger","operationId":"updatePassenger","parameters":[{"name":"id","in":"path","required":true,"schema":{"type":"integer","format":"int64"}}],"requestBody":{"content":{"application/json":{"schema":{"$ref":"#/components/schemas/Passenger"}}},"required":true},"responses":{"200":{"description":"OK","content":{"*/*":{"schema":{"$ref":"#/components/schemas/Passenger"}}}}}},"delete":{"tags":["Passenger"],"summary":"Delete a passenger","description":"Deletes a passenger","operationId":"deletePassenger","parameters":[{"name":"id","in":"path","required":true,"schema":{"type":"integer","format":"int64"}}],"responses":{"200":{"description":"OK"}}}},"/bookings/{id}":{"get":{"tags":["Booking"],"summary":"Get a booking by ID","description":"Returns a single booking","operationId":"getBookingById","parameters":[{"name":"id","in":"path","required":true,"schema":{"type":"integer","format":"int64"}}],"responses":{"200":{"description":"Successfully retrieved booking","content":{"*/*":{"schema":{"$ref":"#/components/schemas/Booking"}}}},"404":{"description":"Booking not found","content":{"*/*":{"schema":{"$ref":"#/components/schemas/Booking"}}}}}},"put":{"tags":["Booking"],"summary":"Update an existing booking","description":"Updates an existing booking","operationId":"updateBooking","parameters":[{"name":"id","in":"path","required":true,"schema":{"type":"integer","format":"int64"}}],"requestBody":{"content":{"application/json":{"schema":{"$ref":"#/components/schemas/Booking"}}},"required":true},"responses":{"200":{"description":"OK","content":{"*/*":{"schema":{"$ref":"#/components/schemas/Booking"}}}}}},"delete":{"tags":["Booking"],"summary":"Delete a booking","description":"Deletes a booking","operationId":"deleteBooking","parameters":[{"name":"id","in":"path","required":true,"schema":{"type":"integer","format":"int64"}}],"responses":{"200":{"description":"OK"}}}},"/booking-passengers/{id}":{"get":{"tags":["Booking Passenger"],"summary":"Get a booking passenger by ID","description":"Returns a single booking passenger","operationId":"getBookingPassengerById","parameters":[{"name":"id","in":"path","required":true,"schema":{"type":"integer","format":"int64"}}],"responses":{"200":{"description":"Successfully retrieved booking passenger","content":{"*/*":{"schema":{"$ref":"#/components/schemas/BookingPassenger"}}}},"404":{"description":"Booking passenger not found","content":{"*/*":{"schema":{"$ref":"#/components/schemas/BookingPassenger"}}}}}},"put":{"tags":["Booking Passenger"],"summary":"Update an existing booking passenger","description":"Updates an existing booking passenger","operationId":"updateBookingPassenger","parameters":[{"name":"id","in":"path","required":true,"schema":{"type":"integer","format":"int64"}}],"requestBody":{"content":{"application/json":{"schema":{"$ref":"#/components/schemas/BookingPassenger"}}},"required":true},"responses":{"200":{"description":"OK","content":{"*/*":{"schema":{"$ref":"#/components/schemas/BookingPassenger"}}}}}},"delete":{"tags":["Booking Passenger"],"summary":"Delete a booking passenger","description":"Deletes a booking passenger","operationId":"deleteBookingPassenger","parameters":[{"name":"id","in":"path","required":true,"schema":{"type":"integer","format":"int64"}}],"responses":{"200":{"description":"OK"}}}},"/seat-inventories":{"get":{"tags":["Seat Inventory"],"summary":"Get all seat inventories","description":"Returns a list of all seat inventories","operationId":"getAllSeatInventories","responses":{"200":{"description":"OK","content":{"*/*":{"schema":{"type":"array","items":{"$ref":"#/components/schemas/SeatInventory"}}}}}}},"post":{"tags":["Seat Inventory"],"summary":"Create a new seat inventory","description":"Creates a new seat inventory","operationId":"createSeatInventory","requestBody":{"content":{"application/json":{"schema":{"$ref":"#/components/schemas/SeatInventory"}}},"required":true},"responses":{"200":{"description":"OK","content":{"*/*":{"schema":{"$ref":"#/components/schemas/SeatInventory"}}}}}}},"/seat-inventories/lock":{"post":{"tags":["Seat Inventory"],"summary":"Lock a seat","description":"Locks a seat for a given flight instance","operationId":"lockSeat","parameters":[{"name":"flightInstanceId","in":"query","required":true,"schema":{"type":"integer","format":"int64"}},{"name":"seatNumber","in":"query","required":true,"schema":{"type":"string"}},{"name":"lockDurationMinutes","in":"query","required":false,"schema":{"type":"integer","format":"int64","default":5}}],"responses":{"200":{"description":"Seat locked successfully","content":{"*/*":{"schema":{"type":"string"}}}},"409":{"description":"Seat is already locked","content":{"*/*":{"schema":{"type":"string"}}}}}}},"/passengers":{"get":{"tags":["Passenger"],"summary":"Get all passengers","description":"Returns a list of all passengers","operationId":"getAllPassengers","responses":{"200":{"description":"OK","content":{"*/*":{"schema":{"type":"array","items":{"$ref":"#/components/schemas/Passenger"}}}}}}},"post":{"tags":["Passenger"],"summary":"Create a new passenger","description":"Creates a new passenger","operationId":"createPassenger","requestBody":{"content":{"application/json":{"schema":{"$ref":"#/components/schemas/Passenger"}}},"required":true},"responses":{"200":{"description":"OK","content":{"*/*":{"schema":{"$ref":"#/components/schemas/Passenger"}}}}}}},"/bookings":{"get":{"tags":["Booking"],"summary":"Get all bookings","description":"Returns a list of all bookings","operationId":"getAllBookings","responses":{"200":{"description":"OK","content":{"*/*":{"schema":{"type":"array","items":{"$ref":"#/components/schemas/Booking"}}}}}}},"post":{"tags":["Booking"],"summary":"Create a new booking","description":"Creates a new booking","operationId":"createBooking","requestBody":{"content":{"application/json":{"schema":{"$ref":"#/components/schemas/Booking"}}},"required":true},"responses":{"200":{"description":"OK","content":{"*/*":{"schema":{"$ref":"#/components/schemas/Booking"}}}}}}},"/booking-passengers":{"get":{"tags":["Booking Passenger"],"summary":"Get all booking passengers","description":"Returns a list of all booking passengers","operationId":"getAllBookingPassengers","responses":{"200":{"description":"OK","content":{"*/*":{"schema":{"type":"array","items":{"$ref":"#/components/schemas/BookingPassenger"}}}}}}},"post":{"tags":["Booking Passenger"],"summary":"Create a new booking passenger","description":"Creates a new booking passenger","operationId":"createBookingPassenger","requestBody":{"content":{"application/json":{"schema":{"$ref":"#/components/schemas/BookingPassenger"}}},"required":true},"responses":{"200":{"description":"OK","content":{"*/*":{"schema":{"$ref":"#/components/schemas/BookingPassenger"}}}}}}},"/seat-inventories/status":{"get":{"tags":["Seat Inventory"],"summary":"Get seat status","description":"Gets the status of a seat","operationId":"getSeatStatus","parameters":[{"name":"flightInstanceId","in":"query","required":true,"schema":{"type":"integer","format":"int64"}},{"name":"seatNumber","in":"query","required":true,"schema":{"type":"string"}}],"responses":{"200":{"description":"OK","content":{"*/*":{"schema":{"type":"string"}}}}}}}},"components":{"schemas":{"SeatInventory":{"type":"object","properties":{"seatInventoryId":{"type":"integer","format":"int64"},"flightInstanceId":{"type":"integer","format":"int64"},"seatNumber":{"type":"string"},"seatClass":{"type":"string","enum":["ECONOMY","BUSINESS","FIRST"]},"status":{"type":"string","enum":["AVAILABLE","LOCKED","BOOKED"]},"lockedUntil":{"type":"string","format":"date-time"}}},"Passenger":{"type":"object","properties":{"passengerId":{"type":"integer","format":"int64"},"firstName":{"type":"string"},"lastName":{"type":"string"},"dob":{"type":"string","format":"date-time"},"passportNumber":{"type":"string"},"nationality":{"type":"string"}}},"Booking":{"type":"object","properties":{"bookingId":{"type":"integer","format":"int64"},"bookingReference":{"type":"string"},"userId":{"type":"integer","format":"int64"},"flightInstanceId":{"type":"integer","format":"int64"},"status":{"type":"string","enum":["INITIATED","CONFIRMED","CANCELLED"]},"totalPrice":{"type":"number"},"createdAt":{"type":"string","format":"date-time"}}},"BookingPassenger":{"type":"object","properties":{"bookingPassengerId":{"type":"integer","format":"int64"},"booking":{"$ref":"#/components/schemas/Booking"},"passenger":{"$ref":"#/components/schemas/Passenger"},"seatNumber":{"type":"string"},"fareClass":{"type":"string"},"ticketNumber":{"type":"string"}}}}}}